{
  "listing_id": 20,
  "listing_name": "LSG-PNK Life of a Showgirl",
  "count": 7,
  "images": [
    {
      "id": 77,
      "filename": "Life_of_a_Showgirl_-_Main.jpg",
      "original_filename": "Life of a Showgirl - Main",
      "github_url": "https://github.com/CammyCodes/amazon-product-images/blob/main/images/2025/10/Life_of_a_Showgirl_-_Main.jpg",
      "raw_url": "https://raw.githubusercontent.com/CammyCodes/amazon-product-images/main/images/2025/10/Life_of_a_Showgirl_-_Main.jpg",
      "upload_date": "2025-10-15T12:36:25.393081",
      "file_size": 120386,
      "tags": [],
      "collection_id": 20,
      "collection_name": "LSG-PNK Life of a Showgirl",
      "image_position": 1,
      "is_main": true
    },
    {
      "id": 79,
      "filename": "Life_of_a_Showgirl_-_2-1.jpg",
      "original_filename": "Life of a Showgirl - 2",
      "github_url": "https://github.com/CammyCodes/amazon-product-images/blob/main/images/2025/10/Life_of_a_Showgirl_-_2-1.jpg",
      "raw_url": "https://raw.githubusercontent.com/CammyCodes/amazon-product-images/main/images/2025/10/Life_of_a_Showgirl_-_2-1.jpg",
      "upload_date": "2025-10-15T12:36:28.910305",
      "file_size": 158726,
      "tags": [],
      "collection_id": 20,
      "collection_name": "LSG-PNK Life of a Showgirl",
      "image_position": 2,
      "is_main": false
    },
    {
      "id": 78,
      "filename": "Life_of_a_Showgirl_-_2.jpg",
      "original_filename": "Life of a Showgirl - 2",
      "github_url": "https://github.com/CammyCodes/amazon-product-images/blob/main/images/2025/10/Life_of_a_Showgirl_-_2.jpg",
      "raw_url": "https://raw.githubusercontent.com/CammyCodes/amazon-product-images/main/images/2025/10/Life_of_a_Showgirl_-_2.jpg",
      "upload_date": "2025-10-15T12:36:27.918241",
      "file_size": 156026,
      "tags": [],
      "collection_id": 20,
      "collection_name": "LSG-PNK Life of a Showgirl",
      "image_position": 2,
      "is_main": false
    },
    {
      "id": 81,
      "filename": "Life_of_a_Showgirl_-_3-1.jpg",
      "original_filename": "Life of a Showgirl - 3",
      "github_url": "https://github.com/CammyCodes/amazon-product-images/blob/main/images/2025/10/Life_of_a_Showgirl_-_3-1.jpg",
      "raw_url": "https://raw.githubusercontent.com/CammyCodes/amazon-product-images/main/images/2025/10/Life_of_a_Showgirl_-_3-1.jpg",
      "upload_date": "2025-10-15T12:36:31.854170",
      "file_size": 205706,
      "tags": [],
      "collection_id": 20,
      "collection_name": "LSG-PNK Life of a Showgirl",
      "image_position": 3,
      "is_main": false
    },
    {
      "id": 80,
      "filename": "Life_of_a_Showgirl_-_3.jpg",
      "original_filename": "Life of a Showgirl - 3",
      "github_url": "https://github.com/CammyCodes/amazon-product-images/blob/main/images/2025/10/Life_of_a_Showgirl_-_3.jpg",
      "raw_url": "https://raw.githubusercontent.com/CammyCodes/amazon-product-images/main/images/2025/10/Life_of_a_Showgirl_-_3.jpg",
      "upload_date": "2025-10-15T12:36:30.588562",
      "file_size": 228152,
      "tags": [],
      "collection_id": 20,
      "collection_name": "LSG-PNK Life of a Showgirl",
      "image_position": 3,
      "is_main": false
    },
    {
      "id": 82,
      "filename": "Life_of_a_Showgirl_-_4.jpg",
      "original_filename": "Life of a Showgirl - 4",
      "github_url": "https://github.com/CammyCodes/amazon-product-images/blob/main/images/2025/10/Life_of_a_Showgirl_-_4.jpg",
      "raw_url": "https://raw.githubusercontent.com/CammyCodes/amazon-product-images/main/images/2025/10/Life_of_a_Showgirl_-_4.jpg",
      "upload_date": "2025-10-15T12:36:33.159630",
      "file_size": 211885,
      "tags": [],
      "collection_id": 20,
      "collection_name": "LSG-PNK Life of a Showgirl",
      "image_position": 4,
      "is_main": false
    },
    {
      "id": 83,
      "filename": "Life_of_a_Showgirl_-_5.jpg",
      "original_filename": "Life of a Showgirl - 5",
      "github_url": "https://github.com/CammyCodes/amazon-product-images/blob/main/images/2025/10/Life_of_a_Showgirl_-_5.jpg",
      "raw_url": "https://raw.githubusercontent.com/CammyCodes/amazon-product-images/main/images/2025/10/Life_of_a_Showgirl_-_5.jpg",
      "upload_date": "2025-10-15T12:36:35.175556",
      "file_size": 206253,
      "tags": [],
      "collection_id": 20,
      "collection_name": "LSG-PNK Life of a Showgirl",
      "image_position": 5,
      "is_main": false
    }
  ],
  "draft": {
    "collection_id": 20,
    "title": "Willow Gifts Vintage Showgirl Mug - Art Deco Style Pink Coffee Cup For Women - Fun Retro Music Fan Drinkware - Perfect Birthday Or Christmas Present For Her - 11oz Ceramic Tea Novelty Gift",
    "description": "Step into the spotlight with our 'Life of a Showgirl' mug! This stunning piece features a <b>bold Art Deco design</b> in vibrant pink and black, capturing a vintage theatrical spirit. It's the perfect way to celebrate your favourite music eras and add a dash of glamour to your morning routine.<br><br>Made from <b>premium quality ceramic</b> with a contrasting black handle and rim, this 11oz mug is as durable as it is stylish. It\u2019s both <b>dishwasher and microwave safe</b>, making it a practical choice for everyday use. Whether you're buying for yourself or looking for the <b>perfect gift for a fellow fan</b>, this mug is sure to delight.",
    "keywords": "swiftie eras tour tortured poets department album singer songwriter lyrics lover reputation folklore evermore midnights friendship bracelet teacup beverage hot drinks morning breakfast kitchen home office workplace desk accessory mum sister daughter friend colleague boss girlfriend wife student teenager secret santa stocking filler leaving work mothers day valentines day anniversary congratulations thank you theatre musical burlesque dancer performer glamourous twenties 20s gatsby",
    "bullets": [
      "Chic Retro Design \u2013 Embrace vintage glamour with this Art Deco inspired 'Life of a Showgirl' design- a perfect gift for music lovers and fans of iconic pop eras and tours.",
      "Premium Ceramic Quality \u2013 Crafted from high-grade ceramic this durable 11oz mug features a stylish black rim and handle providing a comfortable and sturdy feel for every sip.",
      "Effortless Daily Use \u2013 Designed for your convenience this cup is completely dishwasher and microwave safe making it the ideal choice for your daily tea coffee or hot chocolate.",
      "Vibrant Lasting Print \u2013 Our expert printing process ensures the pink and black Art Deco graphics remain sharp and vibrant wash after wash promising a design that will not fade.",
      "Versatile Gift Idea \u2013 Arriving securely packaged this mug is ready for gifting and is perfect for adding a touch of personality to any home office desk or kitchen setting."
    ],
    "parent_sku": "LSG-PNK-PARENT",
    "platform": "willow",
    "handle_colors": [
      "white"
    ],
    "variations": [
      {
        "color": "Black",
        "ean": "5056634372568",
        "lineNumber": 1,
        "size": "N/A",
        "sku": "LSG-TAY-MUG-BLK-SUB1968",
        "title": "Life Of A Showgirl Vintage Show Sign Popstar Signer Classic Colours Design BLACK MUG"
      }
    ],
    "bulk_input": "5056634372568\t\tLife Of A Showgirl Vintage Show Sign Popstar Signer Classic Colours Design BLACK MUG\t\tLSG-TAY-MUG-BLK-SUB1968",
    "saved_at": "2025-10-20T13:01:04.492Z"
  }
}